rehydra_plugins/rehydra_joblib_launcher/__init__.py
rehydra_plugins/rehydra_joblib_launcher/_core.py
rehydra_plugins/rehydra_joblib_launcher/config.py
rehydra_plugins/rehydra_joblib_launcher/joblib_launcher.py
rehydra_plugins/rehydra_joblib_launcher/py.typed
rehydra_joblib_launcher-1.3.0.dist-info/METADATA
rehydra_joblib_launcher-1.3.0.dist-info/WHEEL
rehydra_joblib_launcher-1.3.0.dist-info/top_level.txt
rehydra_joblib_launcher-1.3.0.dist-info/RECORD
